./2420_process.log
./PKG-INFO
./README.md
./language.json
./math_server.py
./ollama_client.py
./package_name
./push_info.json
./pyproject.toml
./server_config.json
./setup.py
iflow_mcp_rajeevchandra_mcp_client_server_example-0.1.1.dist-info/METADATA
iflow_mcp_rajeevchandra_mcp_client_server_example-0.1.1.dist-info/WHEEL
iflow_mcp_rajeevchandra_mcp_client_server_example-0.1.1.dist-info/entry_points.txt
iflow_mcp_rajeevchandra_mcp_client_server_example-0.1.1.dist-info/RECORD
