Metadata-Version: 2.4
Name: iflow-mcp-rajeevchandra-mcp-client-server-example
Version: 0.1.1
Summary: MCP Server example with add and multiply tools
Requires-Python: >=3.11
Requires-Dist: mcp>=1.0.0
